main.py
MedTrack/doctor/__init__.py
MedTrack/doctor/prescription.py
MedTrack/doctor/report.py
MedTrack/patient/__init__.py
MedTrack/patient/medication.py
MedTrack/patient/reminder.py
MedTrack-0.0.1.dist-info/LICENSE.txt
MedTrack-0.0.1.dist-info/METADATA
MedTrack-0.0.1.dist-info/WHEEL
MedTrack-0.0.1.dist-info/top_level.txt
MedTrack-0.0.1.dist-info/RECORD
