Metadata-Version: 2.1
Name: MedTrack
Version: 0.0.1
Summary: A medecine management system
Author-email: Hanwen Zhang <wzha258@aucklanduni.ac.nz>, Zerui Zhang <zzerui96@gmail.com>
Project-URL: Homepage, https://github.com/HHWZHANG/MedTrack.git
Classifier: Programming Language :: Python :: 3
Classifier: License :: OSI Approved :: MIT License
Classifier: Operating System :: OS Independent
Requires-Python: >=3.8
License-File: LICENSE.txt
